pyfeng/__init__.py
pyfeng/asian.py
pyfeng/assetalloc.py
pyfeng/bsm.py
pyfeng/cev.py
pyfeng/ex.py
pyfeng/gamma.py
pyfeng/garch.py
pyfeng/heston.py
pyfeng/heston_mc.py
pyfeng/heston_mixture.py
pyfeng/mgf2mom.py
pyfeng/multiasset.py
pyfeng/multiasset_Ju2002.py
pyfeng/multiasset_mc.py
pyfeng/norm.py
pyfeng/nsvh.py
pyfeng/opt_abc.py
pyfeng/opt_smile_abc.py
pyfeng/ousv.py
pyfeng/quad.py
pyfeng/rheston.py
pyfeng/rheston_mc.py
pyfeng/sabr.py
pyfeng/sabr_int.py
pyfeng/sabr_mc.py
pyfeng/subord_bm.py
pyfeng/sv32_mc2.py
pyfeng/sv_abc.py
pyfeng/sv_fft.py
pyfeng/svi.py
pyfeng/util.py
pyfeng/data/heston_benchmark.xlsx
pyfeng/data/ousv_benchmark.xlsx
pyfeng/data/sabr_benchmark.xlsx
pyfeng-0.3.0.dist-info/LICENSE
pyfeng-0.3.0.dist-info/METADATA
pyfeng-0.3.0.dist-info/WHEEL
pyfeng-0.3.0.dist-info/top_level.txt
pyfeng-0.3.0.dist-info/RECORD
