Metadata-Version: 2.1
Name: pyfeng
Version: 0.3.0
Summary: Python Financial Engineering
Home-page: https://github.com/PyFE/PyFENG
Author: Jaehyuk Choi
Author-email: pyfe@eml.cc
Project-URL: Documentation, https://pyfeng.readthedocs.io/
Project-URL: Bug Tracker, https://github.com/PyFE/PyFENG/issues
License-File: LICENSE
Requires-Dist: numpy
Requires-Dist: scipy
Requires-Dist: pandas
